Metadata-Version: 1.0
Name: pyinstailor
Version: 1.0
Summary: pyinstailor is a tailor to replace files directly in the executable file generated by PyInstaller.
Home-page: https://github.com/dashingsoft/pyinstailor
Author: Jondy Zhao
Author-email: jondy.zhao@gmail.com
License: UNKNOWN
Platform: UNKNOWN
